dlutils/__init__.py
dlutils/async.py
dlutils/async_calls.py
dlutils/batch_provider.py
dlutils/block_process.py
dlutils/cache.py
dlutils/default_cfg.py
dlutils/download.py
dlutils/epoch.py
dlutils/measures.py
dlutils/numpy_dataset.py
dlutils/optim.py
dlutils/progress_bar.py
dlutils/random_rotation.py
dlutils/reader.py
dlutils/registry.py
dlutils/save_image.py
dlutils/shuffle.py
dlutils/timer.py
dlutils/tracker.py
dlutils/pytorch/__init__.py
dlutils/pytorch/checkpointer.py
dlutils/pytorch/count_parameters.py
dlutils/pytorch/cuda_helper.py
dlutils/pytorch/jacobian.py
dlutils/pytorch/launcher.py
dlutils/pytorch/lr_eq.py
dlutils/pytorch/lr_eq_adam.py
dlutils/pytorch/lr_eq_sgd.py
dlutils/tf/__init__.py
dlutils/tf/matconvnet2tf.py
dlutils/tf/matconvnet2tf_test.py
dlutils/tf/matrix_exponential.py
dlutils-0.0.11.dist-info/LICENSE.txt
dlutils-0.0.11.dist-info/METADATA
dlutils-0.0.11.dist-info/WHEEL
dlutils-0.0.11.dist-info/top_level.txt
dlutils-0.0.11.dist-info/RECORD
