Metadata-Version: 2.1
Name: dlutils
Version: 0.0.11
Summary: dlutils - collection of boilerplate code, usefull primitives, helpers.
Home-page: https://github.com/podgorskiy/dlutils
Author: Stanislav Pidhorskyi
Author-email: stanislav@podgorskiy.com
License: MIT
Keywords: deep-learning pytorch tensorflow
Platform: UNKNOWN
Classifier: Development Status :: 3 - Alpha
Classifier: License :: OSI Approved :: Apache Software License
Classifier: Programming Language :: Python :: 2.7
Classifier: Programming Language :: Python :: 3.6
Classifier: Programming Language :: Python :: 3.7
Classifier: Programming Language :: Python :: 3.8
Classifier: Topic :: Scientific/Engineering :: Artificial Intelligence
